{"101A":{"title":"Designation of the Rules."},"107":{"title":"Effect of repeal of validating statutes."},"104":{"title":"Continuation of existing institutions, rights, and liabilities."},"105":{"title":"Effect on private or local acts."},"108":{"title":"Distribution of Code, Rules, and supplements."},"110":{"title":"Supplements as part of Code."},"103":{"title":"Repeal of prior laws."},"102":{"title":"Effective date of Code."},"101":{"title":"Designation and citation of Code."},"109":{"title":"Amendments to Code."},"106":{"title":"Effect on acts heretofore repealed."}}