{"title":"Fox Theatre, St. Louis, MO 12-10-71","description":"Fox Theatre, St. Louis, MO 12-10-71 is a live album by the rock band the Grateful Dead. As the title suggests, it was recorded at the Fox Theatre in St. Louis, Missouri on December 10, 1971. It was released as a three-disc CD and digitally on October 1, 2021, and will be released as a five-disc LP on November 19, 2021.","imageURL":"https://upload.wikimedia.org/wikipedia/en/thumb/6/68/Fox-Theatre-St-Louis-MO-12-10-71.jpg/220px-Fox-Theatre-St-Louis-MO-12-10-71.jpg","properties":{"artist":"Grateful Dead"},"sources":{"Wikipedia: Fox Theatre, St. Louis, MO 12-10-71":{"homepageURL":"https://en.wikipedia.org/wiki/Fox_Theatre,_St._Louis,_MO_12-10-71"}}}