{"responsibleFireZones":["https://api.weather.gov/zones/fire/ALZ051","https://api.weather.gov/zones/fire/ALZ052","https://api.weather.gov/zones/fire/ALZ053","https://api.weather.gov/zones/fire/ALZ054","https://api.weather.gov/zones/fire/ALZ055","https://api.weather.gov/zones/fire/ALZ056","https://api.weather.gov/zones/fire/ALZ057","https://api.weather.gov/zones/fire/ALZ058","https://api.weather.gov/zones/fire/ALZ059","https://api.weather.gov/zones/fire/ALZ060","https://api.weather.gov/zones/fire/ALZ261","https://api.weather.gov/zones/fire/ALZ262","https://api.weather.gov/zones/fire/ALZ263","https://api.weather.gov/zones/fire/ALZ264","https://api.weather.gov/zones/fire/ALZ265","https://api.weather.gov/zones/fire/ALZ266","https://api.weather.gov/zones/fire/FLZ201","https://api.weather.gov/zones/fire/FLZ202","https://api.weather.gov/zones/fire/FLZ203","https://api.weather.gov/zones/fire/FLZ204","https://api.weather.gov/zones/fire/FLZ205","https://api.weather.gov/zones/fire/FLZ206","https://api.weather.gov/zones/fire/MSZ067","https://api.weather.gov/zones/fire/MSZ075","https://api.weather.gov/zones/fire/MSZ076","https://api.weather.gov/zones/fire/MSZ078","https://api.weather.gov/zones/fire/MSZ079"],"address":{"streetAddress":"8400 Airport Blvd Bldg 11","@type":"PostalAddress","postalCode":"36608","addressLocality":"Mobile","addressRegion":"AL"},"@type":"GovernmentOrganization","telephone":"251-633-6443","responsibleForecastZones":["https://api.weather.gov/zones/forecast/ALZ051","https://api.weather.gov/zones/forecast/ALZ052","https://api.weather.gov/zones/forecast/ALZ053","https://api.weather.gov/zones/forecast/ALZ054","https://api.weather.gov/zones/forecast/ALZ055","https://api.weather.gov/zones/forecast/ALZ056","https://api.weather.gov/zones/forecast/ALZ057","https://api.weather.gov/zones/forecast/ALZ058","https://api.weather.gov/zones/forecast/ALZ059","https://api.weather.gov/zones/forecast/ALZ060","https://api.weather.gov/zones/forecast/ALZ261","https://api.weather.gov/zones/forecast/ALZ262","https://api.weather.gov/zones/forecast/ALZ263","https://api.weather.gov/zones/forecast/ALZ264","https://api.weather.gov/zones/forecast/ALZ265","https://api.weather.gov/zones/forecast/ALZ266","https://api.weather.gov/zones/forecast/FLZ201","https://api.weather.gov/zones/forecast/FLZ202","https://api.weather.gov/zones/forecast/FLZ203","https://api.weather.gov/zones/forecast/FLZ204","https://api.weather.gov/zones/forecast/FLZ205","https://api.weather.gov/zones/forecast/FLZ206","https://api.weather.gov/zones/forecast/GMZ630","https://api.weather.gov/zones/forecast/GMZ631","https://api.weather.gov/zones/forecast/GMZ632","https://api.weather.gov/zones/forecast/GMZ633","https://api.weather.gov/zones/forecast/GMZ634","https://api.weather.gov/zones/forecast/GMZ635","https://api.weather.gov/zones/forecast/GMZ636","https://api.weather.gov/zones/forecast/GMZ650","https://api.weather.gov/zones/forecast/GMZ655","https://api.weather.gov/zones/forecast/GMZ670","https://api.weather.gov/zones/forecast/GMZ675","https://api.weather.gov/zones/forecast/MSZ067","https://api.weather.gov/zones/forecast/MSZ075","https://api.weather.gov/zones/forecast/MSZ076","https://api.weather.gov/zones/forecast/MSZ078","https://api.weather.gov/zones/forecast/MSZ079"],"parentOrganization":"https://api.weather.gov/offices/SRH","@context":{"@vocab":"https://schema.org/","@version":"1.1"},"nwsRegion":"sr","responsibleCounties":["https://api.weather.gov/zones/county/ALC003","https://api.weather.gov/zones/county/ALC013","https://api.weather.gov/zones/county/ALC023","https://api.weather.gov/zones/county/ALC025","https://api.weather.gov/zones/county/ALC035","https://api.weather.gov/zones/county/ALC039","https://api.weather.gov/zones/county/ALC041","https://api.weather.gov/zones/county/ALC053","https://api.weather.gov/zones/county/ALC097","https://api.weather.gov/zones/county/ALC099","https://api.weather.gov/zones/county/ALC129","https://api.weather.gov/zones/county/ALC131","https://api.weather.gov/zones/county/FLC033","https://api.weather.gov/zones/county/FLC091","https://api.weather.gov/zones/county/FLC113","https://api.weather.gov/zones/county/MSC039","https://api.weather.gov/zones/county/MSC041","https://api.weather.gov/zones/county/MSC111","https://api.weather.gov/zones/county/MSC131","https://api.weather.gov/zones/county/MSC153"],"name":"Mobile/Pensacola","faxNumber":"251-406-8612","approvedObservationStations":["https://api.weather.gov/stations/KASD","https://api.weather.gov/stations/KAUO","https://api.weather.gov/stations/KBFM","https://api.weather.gov/stations/KCEW","https://api.weather.gov/stations/KDHN","https://api.weather.gov/stations/KDTS","https://api.weather.gov/stations/KECP","https://api.weather.gov/stations/KGPT","https://api.weather.gov/stations/KGZH","https://api.weather.gov/stations/KHBG","https://api.weather.gov/stations/KHDC","https://api.weather.gov/stations/KHKS","https://api.weather.gov/stations/KJAN","https://api.weather.gov/stations/KMAI","https://api.weather.gov/stations/KMEI","https://api.weather.gov/stations/KMGM","https://api.weather.gov/stations/KMOB","https://api.weather.gov/stations/KMSY","https://api.weather.gov/stations/KNPA","https://api.weather.gov/stations/KNSE","https://api.weather.gov/stations/KPAM","https://api.weather.gov/stations/KPIB","https://api.weather.gov/stations/KPNS","https://api.weather.gov/stations/KPQL","https://api.weather.gov/stations/KPRN","https://api.weather.gov/stations/KTOI","https://api.weather.gov/stations/KVPS"],"@id":"https://api.weather.gov/offices/MOB","id":"MOB","email":"sr-mob.webmaster@noaa.gov","sameAs":"https://www.weather.gov/mob"}