{"25":{"title":"Courts-Appellate"},"5":{"title":"Townships"},"51":{"title":"Public Welfare"},"41":{"title":"Labor and Industry"},"9":{"title":"Agriculture-Animals-Fences"},"43":{"title":"Liquor"},"1":{"title":"State Government"},"29":{"title":"Crimes-Procedure"},"39":{"title":"Insurance"},"55":{"title":"Roads-Highways-Bridges"},"11":{"title":"Banks-Savings and Loan Associations"},"23":{"title":"Courts-Common Pleas"},"57":{"title":"Taxation"},"13":{"title":"Commercial Transactions"},"33":{"title":"Education-Libraries"},"3":{"title":"Counties"},"49":{"title":"Public Utilities"},"19":{"title":"Courts-Municipal-Mayor's-County"},"27":{"title":"Courts-General Provisions-Special Remedies"},"47":{"title":"Occupations-Professions"},"17":{"title":"Corporations-Partnerships"},"59":{"title":"Veterans-Military Affairs"},"21":{"title":"Courts-Probate-Juvenile"},"45":{"title":"Motor Vehicles-Aeronautics-Watercraft"},"37":{"title":"Health-Safety-Morals"},"15":{"title":"Conservation of Natural Resources"},"35":{"title":"Elections"},"7":{"title":"Municipal Corporations"},"31":{"title":"Domestic Relations-Children"},"63":{"title":"Workforce Development"},"53":{"title":"Real Property"},"58":{"title":"Trusts"},"61":{"title":"Water Supply-Sanitation-Ditches"}}