{"afghanistan":{"Military Enlistment Age":{"value":"18 (voluntary)","yearOfData":2020,"sources":{"Wikipedia: List of enlistment age by country":{"homepageURL":"https://en.wikipedia.org/wiki/List_of_enlistment_age_by_country"}}}},"albania":{"Military Enlistment Age":{"value":"19 (voluntary; age lowered to 18 during wartime)","yearOfData":2020,"sources":{"Wikipedia: List of enlistment age by country":{"homepageURL":"https://en.wikipedia.org/wiki/List_of_enlistment_age_by_country"}}}},"algeria":{"Military Enlistment Age":{"value":"17 (voluntary), 19 (compulsory)","yearOfData":2020,"sources":{"Wikipedia: List of enlistment age by country":{"homepageURL":"https://en.wikipedia.org/wiki/List_of_enlistment_age_by_country"}}}},"angola":{"Military Enlistment Age":{"value":"18 (voluntary – men), 20 (voluntary – women), 20 (compulsory – men)","yearOfData":2020,"sources":{"Wikipedia: List of enlistment age by country":{"homepageURL":"https://en.wikipedia.org/wiki/List_of_enlistment_age_by_country"}}}},"antiguaandbarbuda":{"Military Enlistment Age":{"value":"– 18 (voluntary)","yearOfData":2020,"sources":{"Wikipedia: List of enlistment age by country":{"homepageURL":"https://en.wikipedia.org/wiki/List_of_enlistment_age_by_country"}}}},"argentina":{"Military Enlistment Age":{"value":"18 (voluntary)","yearOfData":2020,"sources":{"Wikipedia: List of enlistment age by country":{"homepageURL":"https://en.wikipedia.org/wiki/List_of_enlistment_age_by_country"}}}},"armenia":{"Military Enlistment Age":{"value":"17 (military cadets), 18 (compulsory)","yearOfData":2020,"sources":{"Wikipedia: List of enlistment age by country":{"homepageURL":"https://en.wikipedia.org/wiki/List_of_enlistment_age_by_country"}}}},"australia":{"Military Enlistment Age":{"value":"18 (voluntary; age 17 with parental consent)","yearOfData":2020,"sources":{"Wikipedia: List of enlistment age by country":{"homepageURL":"https://en.wikipedia.org/wiki/List_of_enlistment_age_by_country"}}}},"austria":{"Military Enlistment Age":{"value":"17 (voluntary), 18 (compulsory)","yearOfData":2020,"sources":{"Wikipedia: List of enlistment age by country":{"homepageURL":"https://en.wikipedia.org/wiki/List_of_enlistment_age_by_country"}}}},"azerbaijan":{"Military Enlistment Age":{"value":"17 (voluntary), 18 (compulsory)","yearOfData":2020,"sources":{"Wikipedia: List of enlistment age by country":{"homepageURL":"https://en.wikipedia.org/wiki/List_of_enlistment_age_by_country"}}}},"bahamas":{"Military Enlistment Age":{"value":"18 (voluntary)","yearOfData":2020,"sources":{"Wikipedia: List of enlistment age by country":{"homepageURL":"https://en.wikipedia.org/wiki/List_of_enlistment_age_by_country"}}}},"bahrain":{"Military Enlistment Age":{"value":"15 (military cadets, NCOs and technicians), 18 (other enlistment)","yearOfData":2020,"sources":{"Wikipedia: List of enlistment age by country":{"homepageURL":"https://en.wikipedia.org/wiki/List_of_enlistment_age_by_country"}}}},"bangladesh":{"Military Enlistment Age":{"value":"16 (voluntary)","yearOfData":2020,"sources":{"Wikipedia: List of enlistment age by country":{"homepageURL":"https://en.wikipedia.org/wiki/List_of_enlistment_age_by_country"}}}},"barbados":{"Military Enlistment Age":{"value":"18 (voluntary)","yearOfData":2020,"sources":{"Wikipedia: List of enlistment age by country":{"homepageURL":"https://en.wikipedia.org/wiki/List_of_enlistment_age_by_country"}}}},"belarus":{"Military Enlistment Age":{"value":"17 (military cadets), 18 (compulsory)","yearOfData":2020,"sources":{"Wikipedia: List of enlistment age by country":{"homepageURL":"https://en.wikipedia.org/wiki/List_of_enlistment_age_by_country"}}}},"belgium":{"Military Enlistment Age":{"value":"18 (voluntary)","yearOfData":2020,"sources":{"Wikipedia: List of enlistment age by country":{"homepageURL":"https://en.wikipedia.org/wiki/List_of_enlistment_age_by_country"}}}},"belize":{"Military Enlistment Age":{"value":"18 (voluntary)","yearOfData":2020,"sources":{"Wikipedia: List of enlistment age by country":{"homepageURL":"https://en.wikipedia.org/wiki/List_of_enlistment_age_by_country"}}}},"benin":{"Military Enlistment Age":{"value":"18 (compulsory)","yearOfData":2020,"sources":{"Wikipedia: List of enlistment age by country":{"homepageURL":"https://en.wikipedia.org/wiki/List_of_enlistment_age_by_country"}}}},"bhutan":{"Military Enlistment Age":{"value":"18 (voluntary), 20 (compulsory militia training)","yearOfData":2020,"sources":{"Wikipedia: List of enlistment age by country":{"homepageURL":"https://en.wikipedia.org/wiki/List_of_enlistment_age_by_country"}}}},"bolivia":{"Military Enlistment Age":{"value":"16 (voluntary; pre-military training can start at age 15, providing an exemption from future service; conscription possible at age 14 if there is a shortage of volunteers)","yearOfData":2020,"sources":{"Wikipedia: List of enlistment age by country":{"homepageURL":"https://en.wikipedia.org/wiki/List_of_enlistment_age_by_country"}}}},"bosniaandherzegovina":{"Military Enlistment Age":{"value":"– 18 (voluntary)","yearOfData":2020,"sources":{"Wikipedia: List of enlistment age by country":{"homepageURL":"https://en.wikipedia.org/wiki/List_of_enlistment_age_by_country"}}}},"botswana":{"Military Enlistment Age":{"value":"18 (voluntary)","yearOfData":2020,"sources":{"Wikipedia: List of enlistment age by country":{"homepageURL":"https://en.wikipedia.org/wiki/List_of_enlistment_age_by_country"}}}},"brazil":{"Military Enlistment Age":{"value":"18 (compulsory)","yearOfData":2020,"sources":{"Wikipedia: List of enlistment age by country":{"homepageURL":"https://en.wikipedia.org/wiki/List_of_enlistment_age_by_country"}}}},"brunei":{"Military Enlistment Age":{"value":"17 (voluntary)","yearOfData":2020,"sources":{"Wikipedia: List of enlistment age by country":{"homepageURL":"https://en.wikipedia.org/wiki/List_of_enlistment_age_by_country"}}}},"bulgaria":{"Military Enlistment Age":{"value":"18 (voluntary)","yearOfData":2020,"sources":{"Wikipedia: List of enlistment age by country":{"homepageURL":"https://en.wikipedia.org/wiki/List_of_enlistment_age_by_country"}}}},"burkinafaso":{"Military Enlistment Age":{"value":" 18 (voluntary)","yearOfData":2020,"sources":{"Wikipedia: List of enlistment age by country":{"homepageURL":"https://en.wikipedia.org/wiki/List_of_enlistment_age_by_country"}}}},"burundi":{"Military Enlistment Age":{"value":"18 (voluntary)","yearOfData":2020,"sources":{"Wikipedia: List of enlistment age by country":{"homepageURL":"https://en.wikipedia.org/wiki/List_of_enlistment_age_by_country"}}}},"capeverde":{"Military Enlistment Age":{"value":" 17 (voluntary), 18 (compulsory)","yearOfData":2020,"sources":{"Wikipedia: List of enlistment age by country":{"homepageURL":"https://en.wikipedia.org/wiki/List_of_enlistment_age_by_country"}}}},"cambodia":{"Military Enlistment Age":{"value":"18 (compulsory)","yearOfData":2020,"sources":{"Wikipedia: List of enlistment age by country":{"homepageURL":"https://en.wikipedia.org/wiki/List_of_enlistment_age_by_country"}}}},"cameroon":{"Military Enlistment Age":{"value":"18 (voluntary)","yearOfData":2020,"sources":{"Wikipedia: List of enlistment age by country":{"homepageURL":"https://en.wikipedia.org/wiki/List_of_enlistment_age_by_country"}}}},"canada":{"Military Enlistment Age":{"value":"18 (voluntary; volunteers can join the Reserves and enter the Military Colleges at age 16, or join the regular forces at age 17 with parental consent)","yearOfData":2020,"sources":{"Wikipedia: List of enlistment age by country":{"homepageURL":"https://en.wikipedia.org/wiki/List_of_enlistment_age_by_country"}}}},"centralafricanrepublic":{"Military Enlistment Age":{"value":"– 18 (voluntary)","yearOfData":2020,"sources":{"Wikipedia: List of enlistment age by country":{"homepageURL":"https://en.wikipedia.org/wiki/List_of_enlistment_age_by_country"}}}},"chad":{"Military Enlistment Age":{"value":"18 (voluntary), 20 (compulsory – men), 21 (compulsory – women)","yearOfData":2020,"sources":{"Wikipedia: List of enlistment age by country":{"homepageURL":"https://en.wikipedia.org/wiki/List_of_enlistment_age_by_country"}}}},"chile":{"Military Enlistment Age":{"value":"18 (voluntary)","yearOfData":2020,"sources":{"Wikipedia: List of enlistment age by country":{"homepageURL":"https://en.wikipedia.org/wiki/List_of_enlistment_age_by_country"}}}},"people'srepublicofchina":{"Military Enlistment Age":{"value":" – 18 (compulsory; only registration is compulsory. People do not have to serve in the military)","yearOfData":2020,"sources":{"Wikipedia: List of enlistment age by country":{"homepageURL":"https://en.wikipedia.org/wiki/List_of_enlistment_age_by_country"}}}},"colombia":{"Military Enlistment Age":{"value":"18 (compulsory)","yearOfData":2020,"sources":{"Wikipedia: List of enlistment age by country":{"homepageURL":"https://en.wikipedia.org/wiki/List_of_enlistment_age_by_country"}}}},"comoros":{"Military Enlistment Age":{"value":"18 (voluntary)","yearOfData":2020,"sources":{"Wikipedia: List of enlistment age by country":{"homepageURL":"https://en.wikipedia.org/wiki/List_of_enlistment_age_by_country"}}}},"democraticrepublicofthecongo":{"Military Enlistment Age":{"value":"o – 18 (compulsory)","yearOfData":2020,"sources":{"Wikipedia: List of enlistment age by country":{"homepageURL":"https://en.wikipedia.org/wiki/List_of_enlistment_age_by_country"}}}},"republicofthecongo":{"Military Enlistment Age":{"value":" – 18 (voluntary)","yearOfData":2020,"sources":{"Wikipedia: List of enlistment age by country":{"homepageURL":"https://en.wikipedia.org/wiki/List_of_enlistment_age_by_country"}}}},"côted'ivoire":{"Military Enlistment Age":{"value":" 18 (compulsory; conscription not enforced)","yearOfData":2020,"sources":{"Wikipedia: List of enlistment age by country":{"homepageURL":"https://en.wikipedia.org/wiki/List_of_enlistment_age_by_country"}}}},"croatia":{"Military Enlistment Age":{"value":"18 (voluntary)","yearOfData":2020,"sources":{"Wikipedia: List of enlistment age by country":{"homepageURL":"https://en.wikipedia.org/wiki/List_of_enlistment_age_by_country"}}}},"cuba":{"Military Enlistment Age":{"value":"17 (compulsory)","yearOfData":2020,"sources":{"Wikipedia: List of enlistment age by country":{"homepageURL":"https://en.wikipedia.org/wiki/List_of_enlistment_age_by_country"}}}},"cyprus":{"Military Enlistment Age":{"value":"17 (voluntary), 18 (compulsory for Greek Cypriots only)","yearOfData":2020,"sources":{"Wikipedia: List of enlistment age by country":{"homepageURL":"https://en.wikipedia.org/wiki/List_of_enlistment_age_by_country"}}}},"czechrepublic":{"Military Enlistment Age":{"value":" 18 (voluntary)","yearOfData":2020,"sources":{"Wikipedia: List of enlistment age by country":{"homepageURL":"https://en.wikipedia.org/wiki/List_of_enlistment_age_by_country"}}}},"denmark":{"Military Enlistment Age":{"value":"18 (compulsory)","yearOfData":2020,"sources":{"Wikipedia: List of enlistment age by country":{"homepageURL":"https://en.wikipedia.org/wiki/List_of_enlistment_age_by_country"}}}},"djibouti":{"Military Enlistment Age":{"value":"18 (voluntary; military training can start at age 16)","yearOfData":2020,"sources":{"Wikipedia: List of enlistment age by country":{"homepageURL":"https://en.wikipedia.org/wiki/List_of_enlistment_age_by_country"}}}},"dominicanrepublic":{"Military Enlistment Age":{"value":" 17 (voluntary)","yearOfData":2020,"sources":{"Wikipedia: List of enlistment age by country":{"homepageURL":"https://en.wikipedia.org/wiki/List_of_enlistment_age_by_country"}}}},"ecuador":{"Military Enlistment Age":{"value":"18 (compulsory; conscription is currently suspended until further notice)","yearOfData":2020,"sources":{"Wikipedia: List of enlistment age by country":{"homepageURL":"https://en.wikipedia.org/wiki/List_of_enlistment_age_by_country"}}}},"egypt":{"Military Enlistment Age":{"value":"15 (voluntary), 18 (compulsory)","yearOfData":2020,"sources":{"Wikipedia: List of enlistment age by country":{"homepageURL":"https://en.wikipedia.org/wiki/List_of_enlistment_age_by_country"}}}},"elsalvador":{"Military Enlistment Age":{"value":" 16 (voluntary), 18 (compulsory)","yearOfData":2020,"sources":{"Wikipedia: List of enlistment age by country":{"homepageURL":"https://en.wikipedia.org/wiki/List_of_enlistment_age_by_country"}}}},"equatorialguinea":{"Military Enlistment Age":{"value":" 18 (compulsory)","yearOfData":2020,"sources":{"Wikipedia: List of enlistment age by country":{"homepageURL":"https://en.wikipedia.org/wiki/List_of_enlistment_age_by_country"}}}},"eritrea":{"Military Enlistment Age":{"value":"18 (compulsory)","yearOfData":2020,"sources":{"Wikipedia: List of enlistment age by country":{"homepageURL":"https://en.wikipedia.org/wiki/List_of_enlistment_age_by_country"}}}},"estonia":{"Military Enlistment Age":{"value":"18 (compulsory)","yearOfData":2020,"sources":{"Wikipedia: List of enlistment age by country":{"homepageURL":"https://en.wikipedia.org/wiki/List_of_enlistment_age_by_country"}}}},"eswatini(swaziland)":{"Military Enlistment Age":{"value":" 18 (voluntary)","yearOfData":2020,"sources":{"Wikipedia: List of enlistment age by country":{"homepageURL":"https://en.wikipedia.org/wiki/List_of_enlistment_age_by_country"}}}},"ethiopia":{"Military Enlistment Age":{"value":"18 (voluntary)","yearOfData":2020,"sources":{"Wikipedia: List of enlistment age by country":{"homepageURL":"https://en.wikipedia.org/wiki/List_of_enlistment_age_by_country"}}}},"fiji":{"Military Enlistment Age":{"value":"18 (voluntary)","yearOfData":2020,"sources":{"Wikipedia: List of enlistment age by country":{"homepageURL":"https://en.wikipedia.org/wiki/List_of_enlistment_age_by_country"}}}},"finland":{"Military Enlistment Age":{"value":"18 (compulsory)","yearOfData":2020,"sources":{"Wikipedia: List of enlistment age by country":{"homepageURL":"https://en.wikipedia.org/wiki/List_of_enlistment_age_by_country"}}}},"france":{"Military Enlistment Age":{"value":"18 (voluntary)","yearOfData":2020,"sources":{"Wikipedia: List of enlistment age by country":{"homepageURL":"https://en.wikipedia.org/wiki/List_of_enlistment_age_by_country"}}}},"gabon":{"Military Enlistment Age":{"value":"20 (voluntary).","yearOfData":2020,"sources":{"Wikipedia: List of enlistment age by country":{"homepageURL":"https://en.wikipedia.org/wiki/List_of_enlistment_age_by_country"}}}},"gambia":{"Military Enlistment Age":{"value":"18 (voluntary).","yearOfData":2020,"sources":{"Wikipedia: List of enlistment age by country":{"homepageURL":"https://en.wikipedia.org/wiki/List_of_enlistment_age_by_country"}}}},"georgia":{"Military Enlistment Age":{"value":"18 (compulsory).","yearOfData":2020,"sources":{"Wikipedia: List of enlistment age by country":{"homepageURL":"https://en.wikipedia.org/wiki/List_of_enlistment_age_by_country"}}}},"germany":{"Military Enlistment Age":{"value":"17 (voluntary).","yearOfData":2020,"sources":{"Wikipedia: List of enlistment age by country":{"homepageURL":"https://en.wikipedia.org/wiki/List_of_enlistment_age_by_country"}}}},"ghana":{"Military Enlistment Age":{"value":"18 (voluntary).","yearOfData":2020,"sources":{"Wikipedia: List of enlistment age by country":{"homepageURL":"https://en.wikipedia.org/wiki/List_of_enlistment_age_by_country"}}}},"greece":{"Military Enlistment Age":{"value":"18 (voluntary), 19 (compulsory; conscription age can be lowered to 17 during wartime).","yearOfData":2020,"sources":{"Wikipedia: List of enlistment age by country":{"homepageURL":"https://en.wikipedia.org/wiki/List_of_enlistment_age_by_country"}}}},"guatemala":{"Military Enlistment Age":{"value":"17 (compulsory).","yearOfData":2020,"sources":{"Wikipedia: List of enlistment age by country":{"homepageURL":"https://en.wikipedia.org/wiki/List_of_enlistment_age_by_country"}}}},"guinea":{"Military Enlistment Age":{"value":"18 (voluntary).","yearOfData":2020,"sources":{"Wikipedia: List of enlistment age by country":{"homepageURL":"https://en.wikipedia.org/wiki/List_of_enlistment_age_by_country"}}}},"guinea-bissau":{"Military Enlistment Age":{"value":"16 (voluntary, with parental consent), 18 (compulsory).","yearOfData":2020,"sources":{"Wikipedia: List of enlistment age by country":{"homepageURL":"https://en.wikipedia.org/wiki/List_of_enlistment_age_by_country"}}}},"guyana":{"Military Enlistment Age":{"value":"18 (voluntary).","yearOfData":2020,"sources":{"Wikipedia: List of enlistment age by country":{"homepageURL":"https://en.wikipedia.org/wiki/List_of_enlistment_age_by_country"}}}},"honduras":{"Military Enlistment Age":{"value":"18 (voluntary)","yearOfData":2020,"sources":{"Wikipedia: List of enlistment age by country":{"homepageURL":"https://en.wikipedia.org/wiki/List_of_enlistment_age_by_country"}}}},"hungary":{"Military Enlistment Age":{"value":"18 (voluntary)","yearOfData":2020,"sources":{"Wikipedia: List of enlistment age by country":{"homepageURL":"https://en.wikipedia.org/wiki/List_of_enlistment_age_by_country"}}}},"india":{"Military Enlistment Age":{"value":"17 (voluntary; volunteers can join the Navy at age 16)","yearOfData":2020,"sources":{"Wikipedia: List of enlistment age by country":{"homepageURL":"https://en.wikipedia.org/wiki/List_of_enlistment_age_by_country"}}}},"indonesia":{"Military Enlistment Age":{"value":"18 (voluntary)","yearOfData":2020,"sources":{"Wikipedia: List of enlistment age by country":{"homepageURL":"https://en.wikipedia.org/wiki/List_of_enlistment_age_by_country"}}}},"iran":{"Military Enlistment Age":{"value":"15 (voluntary service in the Basij), 16 (voluntary), 18 and 20 (compulsory)","yearOfData":2020,"sources":{"Wikipedia: List of enlistment age by country":{"homepageURL":"https://en.wikipedia.org/wiki/List_of_enlistment_age_by_country"}}}},"iraq":{"Military Enlistment Age":{"value":"18 (voluntary)","yearOfData":2020,"sources":{"Wikipedia: List of enlistment age by country":{"homepageURL":"https://en.wikipedia.org/wiki/List_of_enlistment_age_by_country"}}}},"ireland":{"Military Enlistment Age":{"value":"18 (voluntary)","yearOfData":2020,"sources":{"Wikipedia: List of enlistment age by country":{"homepageURL":"https://en.wikipedia.org/wiki/List_of_enlistment_age_by_country"}}}},"israel":{"Military Enlistment Age":{"value":"17 (voluntary), 18 (compulsory for Jews and Druze only)","yearOfData":2020,"sources":{"Wikipedia: List of enlistment age by country":{"homepageURL":"https://en.wikipedia.org/wiki/List_of_enlistment_age_by_country"}}}},"italy":{"Military Enlistment Age":{"value":"18 (voluntary)","yearOfData":2020,"sources":{"Wikipedia: List of enlistment age by country":{"homepageURL":"https://en.wikipedia.org/wiki/List_of_enlistment_age_by_country"}}}},"jamaica":{"Military Enlistment Age":{"value":"17 (voluntary)","yearOfData":2020,"sources":{"Wikipedia: List of enlistment age by country":{"homepageURL":"https://en.wikipedia.org/wiki/List_of_enlistment_age_by_country"}}}},"japan":{"Military Enlistment Age":{"value":"18 (voluntary)","yearOfData":2020,"sources":{"Wikipedia: List of enlistment age by country":{"homepageURL":"https://en.wikipedia.org/wiki/List_of_enlistment_age_by_country"}}}},"jordan":{"Military Enlistment Age":{"value":"17 (voluntary)","yearOfData":2020,"sources":{"Wikipedia: List of enlistment age by country":{"homepageURL":"https://en.wikipedia.org/wiki/List_of_enlistment_age_by_country"}}}},"kazakhstan":{"Military Enlistment Age":{"value":"15 (military cadets), 18 (compulsory)","yearOfData":2020,"sources":{"Wikipedia: List of enlistment age by country":{"homepageURL":"https://en.wikipedia.org/wiki/List_of_enlistment_age_by_country"}}}},"kenya":{"Military Enlistment Age":{"value":"18 (voluntary)","yearOfData":2020,"sources":{"Wikipedia: List of enlistment age by country":{"homepageURL":"https://en.wikipedia.org/wiki/List_of_enlistment_age_by_country"}}}},"northkorea":{"Military Enlistment Age":{"value":" 17 (compulsory)","yearOfData":2020,"sources":{"Wikipedia: List of enlistment age by country":{"homepageURL":"https://en.wikipedia.org/wiki/List_of_enlistment_age_by_country"}}}},"southkorea":{"Military Enlistment Age":{"value":" 18 (compulsory)","yearOfData":2020,"sources":{"Wikipedia: List of enlistment age by country":{"homepageURL":"https://en.wikipedia.org/wiki/List_of_enlistment_age_by_country"}}}},"kuwait":{"Military Enlistment Age":{"value":"17 (voluntary)","yearOfData":2020,"sources":{"Wikipedia: List of enlistment age by country":{"homepageURL":"https://en.wikipedia.org/wiki/List_of_enlistment_age_by_country"}}}},"kyrgyzstan":{"Military Enlistment Age":{"value":"16 (military cadets), 18 (compulsory), 19 (voluntary – women)","yearOfData":2020,"sources":{"Wikipedia: List of enlistment age by country":{"homepageURL":"https://en.wikipedia.org/wiki/List_of_enlistment_age_by_country"}}}},"laos":{"Military Enlistment Age":{"value":"18 (compulsory)","yearOfData":2020,"sources":{"Wikipedia: List of enlistment age by country":{"homepageURL":"https://en.wikipedia.org/wiki/List_of_enlistment_age_by_country"}}}},"latvia":{"Military Enlistment Age":{"value":"18 (voluntary)","yearOfData":2020,"sources":{"Wikipedia: List of enlistment age by country":{"homepageURL":"https://en.wikipedia.org/wiki/List_of_enlistment_age_by_country"}}}},"lebanon":{"Military Enlistment Age":{"value":"17 (voluntary)","yearOfData":2020,"sources":{"Wikipedia: List of enlistment age by country":{"homepageURL":"https://en.wikipedia.org/wiki/List_of_enlistment_age_by_country"}}}},"lesotho":{"Military Enlistment Age":{"value":"18 (voluntary)","yearOfData":2020,"sources":{"Wikipedia: List of enlistment age by country":{"homepageURL":"https://en.wikipedia.org/wiki/List_of_enlistment_age_by_country"}}}},"liberia":{"Military Enlistment Age":{"value":"18 (voluntary)","yearOfData":2020,"sources":{"Wikipedia: List of enlistment age by country":{"homepageURL":"https://en.wikipedia.org/wiki/List_of_enlistment_age_by_country"}}}},"libya":{"Military Enlistment Age":{"value":"18 (voluntary)","yearOfData":2020,"sources":{"Wikipedia: List of enlistment age by country":{"homepageURL":"https://en.wikipedia.org/wiki/List_of_enlistment_age_by_country"}}}},"lithuania":{"Military Enlistment Age":{"value":"18 (compulsory)","yearOfData":2020,"sources":{"Wikipedia: List of enlistment age by country":{"homepageURL":"https://en.wikipedia.org/wiki/List_of_enlistment_age_by_country"}}}},"luxembourg":{"Military Enlistment Age":{"value":"18 (voluntary)","yearOfData":2020,"sources":{"Wikipedia: List of enlistment age by country":{"homepageURL":"https://en.wikipedia.org/wiki/List_of_enlistment_age_by_country"}}}},"madagascar":{"Military Enlistment Age":{"value":"18 (compulsory)","yearOfData":2020,"sources":{"Wikipedia: List of enlistment age by country":{"homepageURL":"https://en.wikipedia.org/wiki/List_of_enlistment_age_by_country"}}}},"malawi":{"Military Enlistment Age":{"value":"18 (voluntary)","yearOfData":2020,"sources":{"Wikipedia: List of enlistment age by country":{"homepageURL":"https://en.wikipedia.org/wiki/List_of_enlistment_age_by_country"}}}},"malaysia":{"Military Enlistment Age":{"value":"17 (voluntary)","yearOfData":2020,"sources":{"Wikipedia: List of enlistment age by country":{"homepageURL":"https://en.wikipedia.org/wiki/List_of_enlistment_age_by_country"}}}},"maldives":{"Military Enlistment Age":{"value":"18 (voluntary)","yearOfData":2020,"sources":{"Wikipedia: List of enlistment age by country":{"homepageURL":"https://en.wikipedia.org/wiki/List_of_enlistment_age_by_country"}}}},"mali":{"Military Enlistment Age":{"value":"18 (compulsory)","yearOfData":2020,"sources":{"Wikipedia: List of enlistment age by country":{"homepageURL":"https://en.wikipedia.org/wiki/List_of_enlistment_age_by_country"}}}},"malta":{"Military Enlistment Age":{"value":"18 (voluntary)","yearOfData":2020,"sources":{"Wikipedia: List of enlistment age by country":{"homepageURL":"https://en.wikipedia.org/wiki/List_of_enlistment_age_by_country"}}}},"mauritania":{"Military Enlistment Age":{"value":"18 (voluntary)","yearOfData":2020,"sources":{"Wikipedia: List of enlistment age by country":{"homepageURL":"https://en.wikipedia.org/wiki/List_of_enlistment_age_by_country"}}}},"mexico":{"Military Enlistment Age":{"value":"16 (voluntary, with parental consent), 18 (compulsory)","yearOfData":2020,"sources":{"Wikipedia: List of enlistment age by country":{"homepageURL":"https://en.wikipedia.org/wiki/List_of_enlistment_age_by_country"}}}},"moldova":{"Military Enlistment Age":{"value":"18 (compulsory)","yearOfData":2020,"sources":{"Wikipedia: List of enlistment age by country":{"homepageURL":"https://en.wikipedia.org/wiki/List_of_enlistment_age_by_country"}}}},"mongolia":{"Military Enlistment Age":{"value":"18 (compulsory)","yearOfData":2020,"sources":{"Wikipedia: List of enlistment age by country":{"homepageURL":"https://en.wikipedia.org/wiki/List_of_enlistment_age_by_country"}}}},"montenegro":{"Military Enlistment Age":{"value":"18 (voluntary)","yearOfData":2020,"sources":{"Wikipedia: List of enlistment age by country":{"homepageURL":"https://en.wikipedia.org/wiki/List_of_enlistment_age_by_country"}}}},"morocco":{"Military Enlistment Age":{"value":"20 (voluntary)","yearOfData":2020,"sources":{"Wikipedia: List of enlistment age by country":{"homepageURL":"https://en.wikipedia.org/wiki/List_of_enlistment_age_by_country"}}}},"mozambique":{"Military Enlistment Age":{"value":"18 (compulsory)","yearOfData":2020,"sources":{"Wikipedia: List of enlistment age by country":{"homepageURL":"https://en.wikipedia.org/wiki/List_of_enlistment_age_by_country"}}}},"myanmar":{"Military Enlistment Age":{"value":"18 (voluntary)","yearOfData":2020,"sources":{"Wikipedia: List of enlistment age by country":{"homepageURL":"https://en.wikipedia.org/wiki/List_of_enlistment_age_by_country"}}}},"namibia":{"Military Enlistment Age":{"value":"18 (voluntary)","yearOfData":2020,"sources":{"Wikipedia: List of enlistment age by country":{"homepageURL":"https://en.wikipedia.org/wiki/List_of_enlistment_age_by_country"}}}},"nepal":{"Military Enlistment Age":{"value":"18 (voluntary)","yearOfData":2020,"sources":{"Wikipedia: List of enlistment age by country":{"homepageURL":"https://en.wikipedia.org/wiki/List_of_enlistment_age_by_country"}}}},"netherlands":{"Military Enlistment Age":{"value":"17 (voluntary)","yearOfData":2020,"sources":{"Wikipedia: List of enlistment age by country":{"homepageURL":"https://en.wikipedia.org/wiki/List_of_enlistment_age_by_country"}}}},"newzealand":{"Military Enlistment Age":{"value":" 17 (voluntary; soldiers are not deployed in combat before the age of 18)","yearOfData":2020,"sources":{"Wikipedia: List of enlistment age by country":{"homepageURL":"https://en.wikipedia.org/wiki/List_of_enlistment_age_by_country"}}}},"nicaragua":{"Military Enlistment Age":{"value":"18 (voluntary)","yearOfData":2020,"sources":{"Wikipedia: List of enlistment age by country":{"homepageURL":"https://en.wikipedia.org/wiki/List_of_enlistment_age_by_country"}}}},"niger":{"Military Enlistment Age":{"value":"18 (compulsory)","yearOfData":2020,"sources":{"Wikipedia: List of enlistment age by country":{"homepageURL":"https://en.wikipedia.org/wiki/List_of_enlistment_age_by_country"}}}},"nigeria":{"Military Enlistment Age":{"value":"18 (voluntary)","yearOfData":2020,"sources":{"Wikipedia: List of enlistment age by country":{"homepageURL":"https://en.wikipedia.org/wiki/List_of_enlistment_age_by_country"}}}},"northmacedonia":{"Military Enlistment Age":{"value":" 18 (voluntary)","yearOfData":2020,"sources":{"Wikipedia: List of enlistment age by country":{"homepageURL":"https://en.wikipedia.org/wiki/List_of_enlistment_age_by_country"}}}},"norway":{"Military Enlistment Age":{"value":"17 (voluntary – men), 18 (voluntary – women), 19 (compulsory; conscription age can be lowered to 16 during wartime)","yearOfData":2020,"sources":{"Wikipedia: List of enlistment age by country":{"homepageURL":"https://en.wikipedia.org/wiki/List_of_enlistment_age_by_country"}}}},"oman":{"Military Enlistment Age":{"value":"18 (voluntary)","yearOfData":2020,"sources":{"Wikipedia: List of enlistment age by country":{"homepageURL":"https://en.wikipedia.org/wiki/List_of_enlistment_age_by_country"}}}},"pakistan":{"Military Enlistment Age":{"value":"16 (voluntary)","yearOfData":2020,"sources":{"Wikipedia: List of enlistment age by country":{"homepageURL":"https://en.wikipedia.org/wiki/List_of_enlistment_age_by_country"}}}},"papuanewguinea":{"Military Enlistment Age":{"value":"– 18 (voluntary; age 16 with parental consent)","yearOfData":2020,"sources":{"Wikipedia: List of enlistment age by country":{"homepageURL":"https://en.wikipedia.org/wiki/List_of_enlistment_age_by_country"}}}},"paraguay":{"Military Enlistment Age":{"value":"18 (compulsory)","yearOfData":2020,"sources":{"Wikipedia: List of enlistment age by country":{"homepageURL":"https://en.wikipedia.org/wiki/List_of_enlistment_age_by_country"}}}},"peru":{"Military Enlistment Age":{"value":"18 (voluntary)","yearOfData":2020,"sources":{"Wikipedia: List of enlistment age by country":{"homepageURL":"https://en.wikipedia.org/wiki/List_of_enlistment_age_by_country"}}}},"philippines":{"Military Enlistment Age":{"value":"17 (voluntary)","yearOfData":2020,"sources":{"Wikipedia: List of enlistment age by country":{"homepageURL":"https://en.wikipedia.org/wiki/List_of_enlistment_age_by_country"}}}},"poland":{"Military Enlistment Age":{"value":"18 (voluntary)","yearOfData":2020,"sources":{"Wikipedia: List of enlistment age by country":{"homepageURL":"https://en.wikipedia.org/wiki/List_of_enlistment_age_by_country"}}}},"portugal":{"Military Enlistment Age":{"value":"18 (voluntary)","yearOfData":2020,"sources":{"Wikipedia: List of enlistment age by country":{"homepageURL":"https://en.wikipedia.org/wiki/List_of_enlistment_age_by_country"}}}},"qatar":{"Military Enlistment Age":{"value":"18 (compulsory)","yearOfData":2020,"sources":{"Wikipedia: List of enlistment age by country":{"homepageURL":"https://en.wikipedia.org/wiki/List_of_enlistment_age_by_country"}}}},"romania":{"Military Enlistment Age":{"value":"18 (voluntary)","yearOfData":2020,"sources":{"Wikipedia: List of enlistment age by country":{"homepageURL":"https://en.wikipedia.org/wiki/List_of_enlistment_age_by_country"}}}},"russia":{"Military Enlistment Age":{"value":"16 (military cadets), 18 (compulsory)","yearOfData":2020,"sources":{"Wikipedia: List of enlistment age by country":{"homepageURL":"https://en.wikipedia.org/wiki/List_of_enlistment_age_by_country"}}}},"rwanda":{"Military Enlistment Age":{"value":"18 (voluntary)","yearOfData":2020,"sources":{"Wikipedia: List of enlistment age by country":{"homepageURL":"https://en.wikipedia.org/wiki/List_of_enlistment_age_by_country"}}}},"saintkittsandnevis":{"Military Enlistment Age":{"value":" – 18 (voluntary)","yearOfData":2020,"sources":{"Wikipedia: List of enlistment age by country":{"homepageURL":"https://en.wikipedia.org/wiki/List_of_enlistment_age_by_country"}}}},"sanmarino":{"Military Enlistment Age":{"value":" 18 (voluntary)","yearOfData":2020,"sources":{"Wikipedia: List of enlistment age by country":{"homepageURL":"https://en.wikipedia.org/wiki/List_of_enlistment_age_by_country"}}}},"sãotoméandpríncipe":{"Military Enlistment Age":{"value":" – 17 (voluntary), 18 (compulsory)","yearOfData":2020,"sources":{"Wikipedia: List of enlistment age by country":{"homepageURL":"https://en.wikipedia.org/wiki/List_of_enlistment_age_by_country"}}}},"saudiarabia":{"Military Enlistment Age":{"value":" 17 (voluntary)","yearOfData":2020,"sources":{"Wikipedia: List of enlistment age by country":{"homepageURL":"https://en.wikipedia.org/wiki/List_of_enlistment_age_by_country"}}}},"senegal":{"Military Enlistment Age":{"value":"18 (voluntary), 20 (compulsory)","yearOfData":2020,"sources":{"Wikipedia: List of enlistment age by country":{"homepageURL":"https://en.wikipedia.org/wiki/List_of_enlistment_age_by_country"}}}},"serbia":{"Military Enlistment Age":{"value":"18 (voluntary)","yearOfData":2020,"sources":{"Wikipedia: List of enlistment age by country":{"homepageURL":"https://en.wikipedia.org/wiki/List_of_enlistment_age_by_country"}}}},"seychelles":{"Military Enlistment Age":{"value":"18 (voluntary)","yearOfData":2020,"sources":{"Wikipedia: List of enlistment age by country":{"homepageURL":"https://en.wikipedia.org/wiki/List_of_enlistment_age_by_country"}}}},"sierraleone":{"Military Enlistment Age":{"value":" 18 (voluntary)","yearOfData":2020,"sources":{"Wikipedia: List of enlistment age by country":{"homepageURL":"https://en.wikipedia.org/wiki/List_of_enlistment_age_by_country"}}}},"singapore":{"Military Enlistment Age":{"value":"16.5 (voluntary), 18 (compulsory)","yearOfData":2020,"sources":{"Wikipedia: List of enlistment age by country":{"homepageURL":"https://en.wikipedia.org/wiki/List_of_enlistment_age_by_country"}}}},"slovakia":{"Military Enlistment Age":{"value":"18 (voluntary)","yearOfData":2020,"sources":{"Wikipedia: List of enlistment age by country":{"homepageURL":"https://en.wikipedia.org/wiki/List_of_enlistment_age_by_country"}}}},"slovenia":{"Military Enlistment Age":{"value":"18 (voluntary)","yearOfData":2020,"sources":{"Wikipedia: List of enlistment age by country":{"homepageURL":"https://en.wikipedia.org/wiki/List_of_enlistment_age_by_country"}}}},"somalia":{"Military Enlistment Age":{"value":"18 (compulsory)","yearOfData":2020,"sources":{"Wikipedia: List of enlistment age by country":{"homepageURL":"https://en.wikipedia.org/wiki/List_of_enlistment_age_by_country"}}}},"southafrica":{"Military Enlistment Age":{"value":" 18 (voluntary)","yearOfData":2020,"sources":{"Wikipedia: List of enlistment age by country":{"homepageURL":"https://en.wikipedia.org/wiki/List_of_enlistment_age_by_country"}}}},"southsudan":{"Military Enlistment Age":{"value":" 18 (compulsory)","yearOfData":2020,"sources":{"Wikipedia: List of enlistment age by country":{"homepageURL":"https://en.wikipedia.org/wiki/List_of_enlistment_age_by_country"}}}},"spain":{"Military Enlistment Age":{"value":"18 (voluntary)","yearOfData":2020,"sources":{"Wikipedia: List of enlistment age by country":{"homepageURL":"https://en.wikipedia.org/wiki/List_of_enlistment_age_by_country"}}}},"srilanka":{"Military Enlistment Age":{"value":" 18 (voluntary)","yearOfData":2020,"sources":{"Wikipedia: List of enlistment age by country":{"homepageURL":"https://en.wikipedia.org/wiki/List_of_enlistment_age_by_country"}}}},"sudan":{"Military Enlistment Age":{"value":"18 (compulsory)","yearOfData":2020,"sources":{"Wikipedia: List of enlistment age by country":{"homepageURL":"https://en.wikipedia.org/wiki/List_of_enlistment_age_by_country"}}}},"suriname":{"Military Enlistment Age":{"value":"18 (voluntary)","yearOfData":2020,"sources":{"Wikipedia: List of enlistment age by country":{"homepageURL":"https://en.wikipedia.org/wiki/List_of_enlistment_age_by_country"}}}},"sweden":{"Military Enlistment Age":{"value":"18 (voluntary)","yearOfData":2020,"sources":{"Wikipedia: List of enlistment age by country":{"homepageURL":"https://en.wikipedia.org/wiki/List_of_enlistment_age_by_country"}}}},"switzerland":{"Military Enlistment Age":{"value":"18 (voluntary), 19 (compulsory)","yearOfData":2020,"sources":{"Wikipedia: List of enlistment age by country":{"homepageURL":"https://en.wikipedia.org/wiki/List_of_enlistment_age_by_country"}}}},"syria":{"Military Enlistment Age":{"value":"18 (compulsory)","yearOfData":2020,"sources":{"Wikipedia: List of enlistment age by country":{"homepageURL":"https://en.wikipedia.org/wiki/List_of_enlistment_age_by_country"}}}},"taiwan":{"Military Enlistment Age":{"value":"18 (compulsory)","yearOfData":2020,"sources":{"Wikipedia: List of enlistment age by country":{"homepageURL":"https://en.wikipedia.org/wiki/List_of_enlistment_age_by_country"}}}},"tajikistan":{"Military Enlistment Age":{"value":"15 (military cadets), 18 (compulsory; military training starts at age 16)","yearOfData":2020,"sources":{"Wikipedia: List of enlistment age by country":{"homepageURL":"https://en.wikipedia.org/wiki/List_of_enlistment_age_by_country"}}}},"tanzania":{"Military Enlistment Age":{"value":"18 (voluntary)","yearOfData":2020,"sources":{"Wikipedia: List of enlistment age by country":{"homepageURL":"https://en.wikipedia.org/wiki/List_of_enlistment_age_by_country"}}}},"thailand":{"Military Enlistment Age":{"value":"18 (voluntary), 21 (compulsory)","yearOfData":2020,"sources":{"Wikipedia: List of enlistment age by country":{"homepageURL":"https://en.wikipedia.org/wiki/List_of_enlistment_age_by_country"}}}},"timor-leste":{"Military Enlistment Age":{"value":"18 (voluntary)","yearOfData":2020,"sources":{"Wikipedia: List of enlistment age by country":{"homepageURL":"https://en.wikipedia.org/wiki/List_of_enlistment_age_by_country"}}}},"togo":{"Military Enlistment Age":{"value":"18 (voluntary)","yearOfData":2020,"sources":{"Wikipedia: List of enlistment age by country":{"homepageURL":"https://en.wikipedia.org/wiki/List_of_enlistment_age_by_country"}}}},"tonga":{"Military Enlistment Age":{"value":"18 (voluntary; age 16 with parental consent)","yearOfData":2020,"sources":{"Wikipedia: List of enlistment age by country":{"homepageURL":"https://en.wikipedia.org/wiki/List_of_enlistment_age_by_country"}}}},"trinidadandtobago":{"Military Enlistment Age":{"value":"– 18 (voluntary; age 16 with parental consent)","yearOfData":2020,"sources":{"Wikipedia: List of enlistment age by country":{"homepageURL":"https://en.wikipedia.org/wiki/List_of_enlistment_age_by_country"}}}},"tunisia":{"Military Enlistment Age":{"value":"18 (voluntary), 20 (compulsory)","yearOfData":2020,"sources":{"Wikipedia: List of enlistment age by country":{"homepageURL":"https://en.wikipedia.org/wiki/List_of_enlistment_age_by_country"}}}},"turkey":{"Military Enlistment Age":{"value":"18 (voluntary), 21 (compulsory)","yearOfData":2020,"sources":{"Wikipedia: List of enlistment age by country":{"homepageURL":"https://en.wikipedia.org/wiki/List_of_enlistment_age_by_country"}}}},"turkmenistan":{"Military Enlistment Age":{"value":"15 (military cadets), 18 (compulsory)","yearOfData":2020,"sources":{"Wikipedia: List of enlistment age by country":{"homepageURL":"https://en.wikipedia.org/wiki/List_of_enlistment_age_by_country"}}}},"uganda":{"Military Enlistment Age":{"value":"18 (voluntary)","yearOfData":2020,"sources":{"Wikipedia: List of enlistment age by country":{"homepageURL":"https://en.wikipedia.org/wiki/List_of_enlistment_age_by_country"}}}},"ukraine":{"Military Enlistment Age":{"value":"20 (compulsory; conscription is planned to be abolished in the future)","yearOfData":2020,"sources":{"Wikipedia: List of enlistment age by country":{"homepageURL":"https://en.wikipedia.org/wiki/List_of_enlistment_age_by_country"}}}},"unitedarabemirates":{"Military Enlistment Age":{"value":"– 17 (voluntary, with consent), 18 (compulsory)","yearOfData":2020,"sources":{"Wikipedia: List of enlistment age by country":{"homepageURL":"https://en.wikipedia.org/wiki/List_of_enlistment_age_by_country"}}}},"unitedkingdom":{"Military Enlistment Age":{"value":" 18 (voluntary; age 16 with parental consent; age 17 for admission to an officer program; Nepalese citizens can join the Brigade of Gurkhas at age 17)","yearOfData":2020,"sources":{"Wikipedia: List of enlistment age by country":{"homepageURL":"https://en.wikipedia.org/wiki/List_of_enlistment_age_by_country"}}}},"unitedstates":{"Military Enlistment Age":{"value":" 18 (voluntary registration), 18 (voluntary service; age 17 with parental consent), 17 (compulsory militia service under 10 U.S. Code § 246)","yearOfData":2020,"sources":{"Wikipedia: List of enlistment age by country":{"homepageURL":"https://en.wikipedia.org/wiki/List_of_enlistment_age_by_country"}}}},"uruguay":{"Military Enlistment Age":{"value":"18 (voluntary)","yearOfData":2020,"sources":{"Wikipedia: List of enlistment age by country":{"homepageURL":"https://en.wikipedia.org/wiki/List_of_enlistment_age_by_country"}}}},"uzbekistan":{"Military Enlistment Age":{"value":"18 (compulsory)","yearOfData":2020,"sources":{"Wikipedia: List of enlistment age by country":{"homepageURL":"https://en.wikipedia.org/wiki/List_of_enlistment_age_by_country"}}}},"venezuela":{"Military Enlistment Age":{"value":"18 (compulsory)","yearOfData":2020,"sources":{"Wikipedia: List of enlistment age by country":{"homepageURL":"https://en.wikipedia.org/wiki/List_of_enlistment_age_by_country"}}}},"vietnam":{"Military Enlistment Age":{"value":"17 (military cadets), 18 (compulsory)","yearOfData":2020,"sources":{"Wikipedia: List of enlistment age by country":{"homepageURL":"https://en.wikipedia.org/wiki/List_of_enlistment_age_by_country"}}}},"vaticancity":{"Military Enlistment Age":{"value":" 19 years old. The Holy See maintains a small volunteer force of Swiss nationals who make up the Pontifical Swiss Guard.","yearOfData":2020,"sources":{"Wikipedia: List of enlistment age by country":{"homepageURL":"https://en.wikipedia.org/wiki/List_of_enlistment_age_by_country"}}}},"yemen":{"Military Enlistment Age":{"value":"18 (voluntary)","yearOfData":2020,"sources":{"Wikipedia: List of enlistment age by country":{"homepageURL":"https://en.wikipedia.org/wiki/List_of_enlistment_age_by_country"}}}},"zambia":{"Military Enlistment Age":{"value":"18 (voluntary; age 16 with parental consent)","yearOfData":2020,"sources":{"Wikipedia: List of enlistment age by country":{"homepageURL":"https://en.wikipedia.org/wiki/List_of_enlistment_age_by_country"}}}},"zimbabwe":{"Military Enlistment Age":{"value":"18 (voluntary)","yearOfData":2020,"sources":{"Wikipedia: List of enlistment age by country":{"homepageURL":"https://en.wikipedia.org/wiki/List_of_enlistment_age_by_country"}}}}}