{"drcongo":{"isEstimate":true,"worldRank":12,"value":84.8,"defcon":1},"belarus":{"isEstimate":true,"worldRank":177,"value":3.2,"defcon":5},"japan":{"isEstimate":true,"worldRank":185,"value":2.5,"defcon":5},"gambia":{"isEstimate":true,"worldRank":33,"value":51.7,"defcon":3},"guinea":{"isEstimate":true,"worldRank":6,"value":98.8,"defcon":1},"estonia":{"isEstimate":true,"worldRank":188,"value":2.4,"defcon":5},"philippines":{"isEstimate":true,"worldRank":68,"value":27.3,"defcon":4},"cuba":{"isEstimate":true,"worldRank":154,"value":5.1,"defcon":5},"mauritius":{"isEstimate":true,"worldRank":99,"value":16,"defcon":5},"mali":{"isEstimate":true,"worldRank":8,"value":94,"defcon":1},"sanmarino":{"isEstimate":true,"worldRank":193,"value":1.7,"defcon":5},"switzerland":{"isEstimate":true,"worldRank":161,"value":4,"defcon":5},"dominicanrepublic":{"isEstimate":true,"worldRank":67,"value":28,"defcon":4},"armenia":{"isEstimate":true,"worldRank":119,"value":11.8,"defcon":5},"vietnam":{"isEstimate":true,"worldRank":84,"value":19.9,"defcon":5},"australia":{"isEstimate":true,"worldRank":171,"value":3.6,"defcon":5},"laos":{"isEstimate":true,"worldRank":42,"value":45.5,"defcon":3},"equatorialguinea":{"isEstimate":true,"worldRank":14,"value":81.8,"defcon":1},"unitedkingdom":{"isEstimate":true,"worldRank":160,"value":4.3,"defcon":5},"newzealand":{"isEstimate":true,"worldRank":157,"value":4.7,"defcon":5},"turkey":{"isEstimate":true,"worldRank":125,"value":10,"defcon":5},"ukraine":{"isEstimate":true,"worldRank":132,"value":8.4,"defcon":5},"austria":{"isEstimate":true,"worldRank":172,"value":3.5,"defcon":5},"northmacedonia":{"isEstimate":true,"worldRank":149,"value":6.1,"defcon":5},"southafrica":{"isEstimate":true,"worldRank":55,"value":34.5,"defcon":4},"cambodia":{"isEstimate":true,"worldRank":69,"value":26.6,"defcon":4},"congo":{"isEstimate":true,"worldRank":39,"value":47.8,"defcon":3},"monaco":{"isEstimate":true,"worldRank":179,"value":3.1,"defcon":5},"hungary":{"isEstimate":true,"worldRank":169,"value":3.7,"defcon":5},"kenya":{"isEstimate":true,"worldRank":47,"value":43.2,"defcon":3},"greece":{"isEstimate":true,"worldRank":163,"value":3.8,"defcon":5},"paraguay":{"isEstimate":true,"worldRank":87,"value":19.4,"defcon":5},"palau":{"isEstimate":true,"worldRank":92,"value":17.3,"defcon":5},"vanuatu":{"isEstimate":true,"worldRank":71,"value":25.9,"defcon":4},"cyprus":{"isEstimate":true,"worldRank":190,"value":2.3,"defcon":5},"colombia":{"isEstimate":true,"worldRank":113,"value":13.8,"defcon":5},"saudiarabia":{"isEstimate":true,"worldRank":145,"value":6.6,"defcon":5},"azerbaijan":{"isEstimate":true,"worldRank":82,"value":20.4,"defcon":4},"syria":{"isEstimate":true,"worldRank":80,"value":21.5,"defcon":4},"rwanda":{"isEstimate":true,"worldRank":56,"value":34.3,"defcon":4},"papuanewguinea":{"isEstimate":true,"worldRank":44,"value":44.8,"defcon":3},"libya":{"isEstimate":true,"worldRank":120,"value":11.5,"defcon":5},"bosniaandherzegovina":{"isEstimate":true,"worldRank":150,"value":5.9,"defcon":5},"norway":{"isEstimate":true,"worldRank":186,"value":2.4,"defcon":5},"afghanistan":{"isEstimate":true,"worldRank":27,"value":60.3,"defcon":2},"kiribati":{"isEstimate":true,"worldRank":34,"value":50.9,"defcon":3},"dominica":{"isEstimate":true,"worldRank":54,"value":34.7,"defcon":4},"bulgaria":{"isEstimate":true,"worldRank":144,"value":6.7,"defcon":5},"bahrain":{"isEstimate":true,"worldRank":143,"value":6.9,"defcon":5},"southkorea":{"isEstimate":true,"worldRank":175,"value":3.2,"defcon":5},"guatemala":{"isEstimate":true,"worldRank":74,"value":24.5,"defcon":4},"ghana":{"isEstimate":true,"worldRank":40,"value":46.2,"defcon":3},"somalia":{"isEstimate":true,"worldRank":2,"value":117,"defcon":1},"jamaica":{"isEstimate":true,"worldRank":111,"value":13.9,"defcon":5},"togo":{"isEstimate":true,"worldRank":23,"value":66.9,"defcon":2},"thailand":{"isEstimate":true,"worldRank":129,"value":9,"defcon":5},"france":{"isEstimate":true,"worldRank":158,"value":4.5,"defcon":5},"serbia":{"isEstimate":true,"worldRank":153,"value":5.3,"defcon":5},"solomonislands":{"isEstimate":true,"worldRank":85,"value":19.7,"defcon":5},"senegal":{"isEstimate":true,"worldRank":43,"value":45.3,"defcon":3},"southsudan":{"isEstimate":true,"worldRank":7,"value":96.2,"defcon":1},"zambia":{"isEstimate":true,"worldRank":26,"value":61.7,"defcon":2},"namibia":{"isEstimate":true,"worldRank":49,"value":42.4,"defcon":3},"comoros":{"isEstimate":true,"worldRank":24,"value":62.9,"defcon":2},"marshallislands":{"isEstimate":true,"worldRank":59,"value":31.8,"defcon":4},"canada":{"isEstimate":true,"worldRank":155,"value":4.9,"defcon":5},"honduras":{"isEstimate":true,"worldRank":95,"value":16.8,"defcon":5},"burkinafaso":{"isEstimate":true,"worldRank":10,"value":87.5,"defcon":1},"maldives":{"isEstimate":true,"worldRank":135,"value":7.6,"defcon":5},"chile":{"isEstimate":true,"worldRank":142,"value":7,"defcon":5},"oman":{"isEstimate":true,"worldRank":121,"value":11.4,"defcon":5},"brazil":{"isEstimate":true,"worldRank":123,"value":11,"defcon":5},"guyana":{"isEstimate":true,"worldRank":65,"value":29.3,"defcon":4},"lesotho":{"isEstimate":true,"worldRank":11,"value":86.4,"defcon":1},"germany":{"isEstimate":true,"worldRank":164,"value":3.8,"defcon":5},"malaysia":{"isEstimate":true,"worldRank":130,"value":8.6,"defcon":5},"peru":{"isEstimate":true,"worldRank":115,"value":13.2,"defcon":5},"india":{"isEstimate":true,"worldRank":57,"value":34.3,"defcon":4},"unitedstates":{"isEstimate":true,"worldRank":147,"value":6.5,"defcon":5},"saintkittsandnevis":{"isEstimate":true,"worldRank":102,"value":15.4,"defcon":5},"denmark":{"isEstimate":true,"worldRank":165,"value":3.8,"defcon":5},"sierraleone":{"isEstimate":true,"worldRank":5,"value":109.2,"defcon":1},"belize":{"isEstimate":true,"worldRank":118,"value":12.3,"defcon":5},"nauru":{"isEstimate":true,"worldRank":60,"value":30.9,"defcon":4},"slovenia":{"isEstimate":true,"worldRank":191,"value":2.1,"defcon":5},"kuwait":{"isEstimate":true,"worldRank":133,"value":7.9,"defcon":5},"haiti":{"isEstimate":true,"worldRank":25,"value":62.8,"defcon":2},"zimbabwe":{"isEstimate":true,"worldRank":32,"value":54.6,"defcon":3},"micronesia":{"isEstimate":true,"worldRank":64,"value":29.4,"defcon":4},"china":{"isEstimate":true,"worldRank":134,"value":7.9,"defcon":5},"bolivia":{"isEstimate":true,"worldRank":70,"value":26,"defcon":4},"brunei":{"isEstimate":true,"worldRank":122,"value":11.4,"defcon":5},"israel":{"isEstimate":true,"worldRank":168,"value":3.7,"defcon":5},"capeverde":{"isEstimate":true,"worldRank":105,"value":14.9,"defcon":5},"bangladesh":{"isEstimate":true,"worldRank":62,"value":30.8,"defcon":4},"ireland":{"isEstimate":true,"worldRank":174,"value":3.3,"defcon":5},"srilanka":{"isEstimate":true,"worldRank":139,"value":7.1,"defcon":5},"sãotoméandpríncipe":{"isEstimate":true,"worldRank":63,"value":29.8,"defcon":4},"albania":{"isEstimate":true,"worldRank":126,"value":9.7,"defcon":5},"poland":{"isEstimate":true,"worldRank":159,"value":4.4,"defcon":5},"eswatini":{"isEstimate":true,"worldRank":38,"value":49.4,"defcon":3},"botswana":{"isEstimate":true,"worldRank":52,"value":41.6,"defcon":3},"costarica":{"isEstimate":true,"worldRank":131,"value":8.6,"defcon":5},"andorra":{"isEstimate":true,"worldRank":181,"value":3,"defcon":5},"venezuela":{"isEstimate":true,"worldRank":75,"value":24.2,"defcon":4},"moldova":{"isEstimate":true,"worldRank":107,"value":14.4,"defcon":5},"malawi":{"isEstimate":true,"worldRank":51,"value":41.6,"defcon":3},"russia":{"isEstimate":true,"worldRank":152,"value":5.8,"defcon":5},"sweden":{"isEstimate":true,"worldRank":183,"value":2.6,"defcon":5},"saintvincentandthegrenadines":{"isEstimate":true,"worldRank":106,"value":14.6,"defcon":5},"madagascar":{"isEstimate":true,"worldRank":36,"value":50.6,"defcon":3},"saintlucia":{"isEstimate":true,"worldRank":79,"value":22.3,"defcon":4},"turkmenistan":{"isEstimate":true,"worldRank":50,"value":42,"defcon":3},"westbank":{"isEstimate":true,"worldRank":86,"value":19.4,"defcon":5},"iran":{"isEstimate":true,"worldRank":112,"value":13.9,"defcon":5},"iraq":{"isEstimate":true,"worldRank":72,"value":25.9,"defcon":4},"seychelles":{"isEstimate":true,"worldRank":108,"value":14.2,"defcon":5},"nicaragua":{"isEstimate":true,"worldRank":97,"value":16.6,"defcon":5},"indonesia":{"isEstimate":true,"worldRank":77,"value":23.9,"defcon":4},"ethiopia":{"isEstimate":true,"worldRank":35,"value":50.7,"defcon":3},"ecuador":{"isEstimate":true,"worldRank":110,"value":14,"defcon":5},"guinea-bissau":{"isEstimate":true,"worldRank":17,"value":78.5,"defcon":2},"spain":{"isEstimate":true,"worldRank":178,"value":3.1,"defcon":5},"mauritania":{"isEstimate":true,"worldRank":21,"value":72.9,"defcon":2},"algeria":{"isEstimate":true,"worldRank":78,"value":23.3,"defcon":4},"mozambique":{"isEstimate":true,"worldRank":20,"value":74.2,"defcon":2},"portugal":{"isEstimate":true,"worldRank":166,"value":3.7,"defcon":5},"cameroon":{"isEstimate":true,"worldRank":18,"value":74.8,"defcon":2},"lithuania":{"isEstimate":true,"worldRank":167,"value":3.7,"defcon":5},"panama":{"isEstimate":true,"worldRank":104,"value":14.9,"defcon":5},"luxembourg":{"isEstimate":true,"worldRank":182,"value":2.8,"defcon":5},"lebanon":{"isEstimate":true,"worldRank":137,"value":7.2,"defcon":5},"mongolia":{"isEstimate":true,"worldRank":100,"value":15.6,"defcon":5},"italy":{"isEstimate":true,"worldRank":180,"value":3.1,"defcon":5},"finland":{"isEstimate":true,"worldRank":187,"value":2.4,"defcon":5},"unitedarabemirates":{"isEstimate":true,"worldRank":136,"value":7.5,"defcon":5},"sudan":{"isEstimate":true,"worldRank":29,"value":58.4,"defcon":3},"benin":{"isEstimate":true,"worldRank":9,"value":90.3,"defcon":1},"nigeria":{"isEstimate":true,"worldRank":1,"value":117.2,"defcon":1},"chad":{"isEstimate":true,"worldRank":3,"value":113.8,"defcon":1},"liberia":{"isEstimate":true,"worldRank":13,"value":84.6,"defcon":1},"djibouti":{"isEstimate":true,"worldRank":30,"value":57.5,"defcon":3},"tajikistan":{"isEstimate":true,"worldRank":58,"value":33.8,"defcon":4},"fiji":{"isEstimate":true,"worldRank":73,"value":25.7,"defcon":4},"singapore":{"isEstimate":true,"worldRank":184,"value":2.5,"defcon":5},"antiguaandbarbuda":{"isEstimate":true,"worldRank":146,"value":6.6,"defcon":5},"mexico":{"isEstimate":true,"worldRank":109,"value":14.2,"defcon":5},"samoa":{"isEstimate":true,"worldRank":103,"value":15,"defcon":5},"trinidadandtobago":{"isEstimate":true,"worldRank":90,"value":17.5,"defcon":5},"elsalvador":{"isEstimate":true,"worldRank":114,"value":13.3,"defcon":5},"tunisia":{"isEstimate":true,"worldRank":94,"value":16.9,"defcon":5},"bahamas":{"isEstimate":true,"worldRank":117,"value":12.6,"defcon":5},"bhutan":{"isEstimate":true,"worldRank":66,"value":28.5,"defcon":4},"ivorycoast":{"isEstimate":true,"worldRank":16,"value":79.3,"defcon":2},"uruguay":{"isEstimate":true,"worldRank":138,"value":7.1,"defcon":5},"uganda":{"isEstimate":true,"worldRank":41,"value":45.8,"defcon":3},"gabon":{"isEstimate":true,"worldRank":48,"value":42.5,"defcon":3},"niger":{"isEstimate":true,"worldRank":15,"value":80.4,"defcon":1},"kyrgyzstan":{"isEstimate":true,"worldRank":88,"value":18.3,"defcon":5},"pakistan":{"isEstimate":true,"worldRank":22,"value":67.2,"defcon":2},"georgia":{"isEstimate":true,"worldRank":127,"value":9.6,"defcon":5},"yemen":{"isEstimate":true,"worldRank":28,"value":58.4,"defcon":3},"centralafricanrepublic":{"isEstimate":true,"worldRank":4,"value":110.1,"defcon":1},"czechrepublic":{"isEstimate":true,"worldRank":176,"value":3.2,"defcon":5},"argentina":{"isEstimate":true,"worldRank":128,"value":9.3,"defcon":5},"jordan":{"isEstimate":true,"worldRank":101,"value":15.6,"defcon":5},"burundi":{"isEstimate":true,"worldRank":31,"value":56.5,"defcon":3},"slovakia":{"isEstimate":true,"worldRank":151,"value":5.8,"defcon":5},"belgium":{"isEstimate":true,"worldRank":173,"value":3.4,"defcon":5},"uzbekistan":{"isEstimate":true,"worldRank":91,"value":17.4,"defcon":5},"tanzania":{"isEstimate":true,"worldRank":37,"value":50.3,"defcon":3},"northkorea":{"isEstimate":true,"worldRank":93,"value":17.3,"defcon":5},"grenada":{"isEstimate":true,"worldRank":98,"value":16.5,"defcon":5},"netherlands":{"isEstimate":true,"worldRank":162,"value":4,"defcon":5},"eritrea":{"isEstimate":true,"worldRank":53,"value":40.5,"defcon":3},"croatia":{"isEstimate":true,"worldRank":156,"value":4.8,"defcon":5},"nepal":{"isEstimate":true,"worldRank":61,"value":30.8,"defcon":4},"morocco":{"isEstimate":true,"worldRank":81,"value":21.4,"defcon":4},"suriname":{"isEstimate":true,"worldRank":89,"value":18,"defcon":5},"romania":{"isEstimate":true,"worldRank":140,"value":7,"defcon":5},"angola":{"isEstimate":true,"worldRank":19,"value":74.7,"defcon":2},"latvia":{"isEstimate":true,"worldRank":170,"value":3.6,"defcon":5},"kazakhstan":{"isEstimate":true,"worldRank":124,"value":10.5,"defcon":5},"easttimor":{"isEstimate":true,"worldRank":46,"value":44.2,"defcon":3},"egypt":{"isEstimate":true,"worldRank":83,"value":20.3,"defcon":4},"malta":{"isEstimate":true,"worldRank":141,"value":7,"defcon":5},"iceland":{"isEstimate":true,"worldRank":192,"value":2,"defcon":5},"myanmar":{"isEstimate":true,"worldRank":45,"value":44.7,"defcon":3},"montenegro":{"isEstimate":true,"worldRank":189,"value":2.3,"defcon":5},"tuvalu":{"isEstimate":true,"worldRank":76,"value":23.9,"defcon":4},"qatar":{"isEstimate":true,"worldRank":148,"value":6.5,"defcon":5},"tonga":{"isEstimate":true,"worldRank":96,"value":16.6,"defcon":5},"barbados":{"isEstimate":true,"worldRank":116,"value":12.7,"defcon":5}}