{"sources":{"Official website":{"homepageURL":"https://humankind.game"},"Wikipedia: Humankind":{"homepageURL":"https://en.wikipedia.org/wiki/Humankind_(video_game)"}},"imageURL":"https://upload.wikimedia.org/wikipedia/en/thumb/0/0f/Humankind_cover_art.jpg/220px-Humankind_cover_art.jpg","description":"Humankind is a 4X video game by Amplitude Studios published by Sega. The game was released for Microsoft Windows, macOS and Stadia in August 2021.","title":"Humankind","youtubeVideoIDs":["jmlaZN0RRiI"],"properties":{"platforms":["Windows","***REMOVED***","Stadia"]}}