{"sources":{"Wikipedia: 2021 FedEx Cup Playoffs":{"homepageURL":"https://en.wikipedia.org/wiki/2021_FedEx_Cup_Playoffs"}},"imageURL":"https://upload.wikimedia.org/wikipedia/en/thumb/a/a4/Flag_of_the_United_States.svg/%quality%px-Flag_of_the_United_States.svg.png","description":"The 2021 FedEx Cup Playoffs, the series of three golf tournaments that will determine the season champion on the U.S.-based PGA Tour, will be played from August 19 \u2013 September 5. It will include the following three events:","title":"2021 FedEx Cup Playoffs"}