{"title":"World War Z: Aftermath","description":"World War Z is a third-person shooter video game developed by Saber Interactive and published by Mad Dog Games. It was released for Microsoft Windows, PlayStation 4 and Xbox One on 16 April 2019, with an upcoming Nintendo Switch release on 2 November 2021. Loosely based on the 2006 book of the same name and set in the same universe as the 2013 film adaptation, the game follows groups of survivors of a zombie apocalypse in the cities of New York, Jerusalem, Moscow, Tokyo and Marseille.","youtubeVideoIDs":["q7BGxc4CTU0","01iyL9HPgBE","zYWxCrL7y3I","nIF1qUri2Bs"],"imageURL":"https://upload.wikimedia.org/wikipedia/en/thumb/4/44/World_War_Z_cover_art.jpg/220px-World_War_Z_cover_art.jpg","properties":{"platforms":["Windows","PlayStation 4","Xbox One"]},"sources":{"Wikipedia: World War Z: Aftermath":{"homepageURL":"https://en.wikipedia.org/wiki/World_War_Z:_Aftermath"},"Official website":{"homepageURL":"http://wwzgame.com/"}}}